tinyllm/__init__.py
tinyllm/exceptions.py
tinyllm/function.py
tinyllm/function_stream.py
tinyllm/prompt_manager.py
tinyllm/state.py
tinyllm/validator.py
tinyllm/agent/__init__.py
tinyllm/agent/agent.py
tinyllm/agent/agent_stream.py
tinyllm/agent/base.py
tinyllm/agent/tool.py
tinyllm/agent/toolkit.py
tinyllm/embeddings/__init__.py
tinyllm/embeddings/models.py
tinyllm/eval/__init__.py
tinyllm/eval/evaluation_model.py
tinyllm/eval/evaluator.py
tinyllm/eval/qa_generator.py
tinyllm/eval/rag_eval_pipeline.py
tinyllm/eval/evaluators/__init__.py
tinyllm/eval/evaluators/answer_accuracy_evaluator.py
tinyllm/eval/evaluators/retrieval_evaluator.py
tinyllm/examples/__init__.py
tinyllm/examples/example_manager.py
tinyllm/examples/example_selector.py
tinyllm/llms/__init__.py
tinyllm/llms/lite_llm.py
tinyllm/llms/lite_llm_stream.py
tinyllm/llms/llm_store.py
tinyllm/memory/__init__.py
tinyllm/memory/memory.py
tinyllm/rag/__init__.py
tinyllm/rag/vector_store.py
tinyllm/rag/document/__init__.py
tinyllm/rag/document/document.py
tinyllm/rag/document/store.py
tinyllm/tests/__init__.py
tinyllm/tests/base.py
tinyllm/tests/test_agent.py
tinyllm/tests/test_agent_stream.py
tinyllm/tests/test_document_store.py
tinyllm/tests/test_embeddings.py
tinyllm/tests/test_evaluators.py
tinyllm/tests/test_example_selector.py
tinyllm/tests/test_fallback_strategy.py
tinyllm/tests/test_function.py
tinyllm/tests/test_litellm.py
tinyllm/tests/test_memory.py
tinyllm/tests/test_tracing.py
tinyllm/tests/test_vector_store.py
tinyllm/tracing/__init__.py
tinyllm/tracing/helpers.py
tinyllm/tracing/langfuse_context.py
tinyllm/util/__init__.py
tinyllm/util/ai_util.py
tinyllm/util/db_util.py
tinyllm/util/fallback_strategy.py
tinyllm/util/helpers.py
tinyllm/util/os_util.py
tinyllm/util/prompt_util.py
tinyllm-1.0.13.dist-info/LICENSE
tinyllm-1.0.13.dist-info/METADATA
tinyllm-1.0.13.dist-info/WHEEL
tinyllm-1.0.13.dist-info/top_level.txt
tinyllm-1.0.13.dist-info/RECORD
